{
  "count": [
    {
      "img": "pc/special-train-zbzz.png",
      "content": 8,
      "unit": "项",
      "title": "装备制造"
    },
    {
      "img": "pc/special-train-jxhg.png",
      "content": 12,
      "unit": "项",
      "title": "精细化工"
    },
    {
      "img": "pc/special-train-swyy.png",
      "content": 24,
      "unit": "项",
      "title": "生物医药"
    },
    {
      "img": "pc/special-train-spjg.png",
      "content": 57,
      "unit": "项",
      "title": "食品加工"
    }
  ],
  "company": [
    "中联重科汉寿工业园",
    "康普药业股份有限公司",
    "康普药业股份有限公司",
    "ss",
    "s2",
    "s3"
  ],
  "typeList": [
    {
      "name": "工业用地",
      "value": "industry"
    },
    {
      "name": "装备制造",
      "value": "make"
    },
    {
      "name": "生物医药",
      "value": "medicine"
    }
  ]
}
